[
  {
    "name": "destiny",
    "datum": "2023-10-06T10:43:16.909Z",
    "score": [
      {
        "djur": "hund",
        "poang": 34.090909090909086
      },
      {
        "djur": "fisk",
        "poang": 34.090909090909086
      },
      {
        "djur": "kanin",
        "poang": 18.181818181818183
      },
      {
        "djur": "katt",
        "poang": 13.636363636363635
      }
    ]
  },
  {
    "name": "jakob",
    "datum": "2023-10-06T10:43:37.885Z",
    "score": [
      {
        "djur": "fisk",
        "poang": 34.090909090909086
      },
      {
        "djur": "katt",
        "poang": 27.27272727272727
      },
      {
        "djur": "hund",
        "poang": 20.454545454545457
      },
      {
        "djur": "kanin",
        "poang": 18.181818181818183
      }
    ]
  }
]